flottille/__init__.py
flottille-0.0.0.dist-info/LICENSE
flottille-0.0.0.dist-info/METADATA
flottille-0.0.0.dist-info/WHEEL
flottille-0.0.0.dist-info/RECORD
