Metadata-Version: 2.1
Name: flottille
Version: 0.0.0
Summary: Flottille is a Python library designed to simplify the development and production deployment of data science and machine learning models
License: MIT
Author: Chris
Author-email: goabonga@pm.me
Requires-Python: >=3.12,<4.0
Classifier: License :: OSI Approved :: MIT License
Classifier: Programming Language :: Python :: 3
Classifier: Programming Language :: Python :: 3.12
Classifier: Programming Language :: Python :: 3.13
